py_messenger_server-0.1.8.data/scripts/server_run
server/__init__.py
server/server.py
server/common/__init__.py
server/common/decorators.py
server/common/descriptors.py
server/common/errors.py
server/common/metaclasses.py
server/common/utils.py
server/common/variables.py
server/doc/__init__.py
server/doc/source/__init__.py
server/doc/source/conf.py
server/log/__init__.py
server/log/server_log_config.py
server/server/__init__.py
server/server/db_server.py
server/server/server_core.py
server/server/server_gui.py
server/unittests/__init__.py
server/unittests/test_utils.py
py_messenger_server-0.1.8.dist-info/METADATA
py_messenger_server-0.1.8.dist-info/WHEEL
py_messenger_server-0.1.8.dist-info/top_level.txt
py_messenger_server-0.1.8.dist-info/RECORD
