Metadata-Version: 2.1
Name: py-messenger-server
Version: 0.1.8
Summary: messenger server
Home-page: UNKNOWN
Author: Murij Kate
Author-email: murij.kat@gmail.com
License: UNKNOWN
Platform: UNKNOWN
Requires-Dist: PyQt5
Requires-Dist: sqlalchemy
Requires-Dist: pycryptodome
Requires-Dist: pycryptodomex
